Workbook

Sheet Model
A1: Veraya — Payments & SaaS Unit Economics
A2: Change the BLUE inputs; everything recalculates. YELLOW cells are the key assumptions to revisit. Defaults model a solid independent (~$1.5M/yr).
A4: INPUTS — the operator & your pricing
A5: Restaurants (live instances) | B5: 10
A6: Avg card volume / restaurant ($/mo) | B6: 120000
A7: Avg ticket / check ($) | B7: 55
A8: → Transactions / restaurant / mo | B8: =B6/B7
A10: SaaS price — base, Models A & B ($/mo) | B10: 349
A11: SaaS price — membership, Model C ($/mo) | B11: 549
A12: Infra cost / restaurant ($/mo) | B12: 40
A14: YOUR PROCESSING COST (what the rails/payfac charge YOU, incl. interchange)
A15: Processing cost — rate (% of volume) | B15: 0.021 | F15: Interchange-plus basis (~2.1%). On vanilla Stripe flat (~2.7%+$0.05) you can't beat Square — the savings story REQUIRES volume interchange-plus.
A16: Processing cost — per transaction ($) | B16: 0.08
A17: → Your processing cost / restaurant ($/mo) | B17: =B15*B6+B16*B8
A19: MERCHANT PRICING MODELS — what YOU charge the restaurant
B20: Rate (%) | C20: Per txn ($)
A21: Model A — Flat % (Square / Toast style) | B21: 0.026 | C21: 0.15 | F21: A: you behave like Square — most revenue, least on-brand.
A22: Model B — Interchange-plus markup (thin) | B22: 0.0015 | C22: 0.05 | F22: B: cost + thin markup — fair, transparent, still beats Square.
A23: Model C — Membership (0% markup) | B23: 0 | C23: 0 | F23: C: process at cost, earn on a higher SaaS tier — 'we don't tax sales.'
A25: PER-RESTAURANT ECONOMICS (monthly)
A26: Metric | B26: A: Flat % | C26: B: Intchg-plus | D26: C: Membership
A27: Merchant pays — processing ($/mo) | B27: =B21*$B$6+C21*$B$8 | C27: =$B$17+(B22*$B$6+C22*$B$8) | D27: =$B$17+(B23*$B$6+C23*$B$8)
A28: Merchant effective rate (%) | B28: =B27/$B$6 | C28: =C27/$B$6 | D28: =D27/$B$6
A29: Your PAYMENTS revenue ($/mo) | B29: =B27-$B$17 | C29: =C27-$B$17 | D29: =D27-$B$17
A30: Your SaaS revenue ($/mo) | B30: =$B$10 | C30: =$B$10 | D30: =$B$11
A31: Your TOTAL revenue ($/mo) | B31: =B29+B30 | C31: =C29+C30 | D31: =D29+D30
A32: Your contribution after infra ($/mo) | B32: =B31-$B$12 | C32: =C31-$B$12 | D32: =D31-$B$12
A34: PER-RESTAURANT (annual) & FLEET
A35: Your total revenue / restaurant ($/yr) | B35: =B31*12 | C35: =C31*12 | D35: =D31*12
A36: Fleet total revenue — × restaurants ($/yr) | B36: =B35*$B$5 | C36: =C35*$B$5 | D36: =D35*$B$5
A37: Fleet contribution after infra ($/yr) | B37: =B32*12*$B$5 | C37: =C32*12*$B$5 | D37: =D32*12*$B$5
A39: MERCHANT VIEW (the sales pitch)
A40: Merchant all-in to Veraya — proc.+SaaS ($/mo) | B40: =B27+B30 | C40: =C27+C30 | D40: =D27+D30
A41: Merchant processing savings vs Square ($/mo) | B41: =$B$27-B27 | C41: =$B$27-C27 | D41: =$B$27-D27
A42: Merchant processing savings vs Square ($/yr) | B42: =B41*12 | C42: =C41*12 | D42: =D41*12
A44: PER AVERAGE CHECK (at avg ticket — the whiteboard example)
A45: Merchant pays per check ($) | B45: =B21*$B$7+C21 | C45: =($B$15*$B$7+$B$16)+(B22*$B$7+C22) | D45: =($B$15*$B$7+$B$16)+(B23*$B$7+C23)
A46: Effective rate per check (%) | B46: =B45/$B$7 | C46: =C45/$B$7 | D46: =D45/$B$7
A47: Saved per check vs Square ($) | B47: =$B$45-B45 | C47: =$B$45-C45 | D47: =$B$45-D45

Sheet Fleet & Scaling
A1: Fleet & Scaling Ramp
A3: RAMP — recommended model: B (interchange-plus). Per-unit economics pulled from the Model sheet.
A4: Restaurants | B4: SaaS rev ($/yr) | C4: Payments rev ($/yr) | D4: Total rev ($/yr) | E4: Contribution ($/yr)
A5: 1 | B5: =A5*Model!$C$30*12 | C5: =A5*Model!$C$29*12 | D5: =A5*Model!$C$35 | E5: =A5*Model!$C$32*12
A6: 3 | B6: =A6*Model!$C$30*12 | C6: =A6*Model!$C$29*12 | D6: =A6*Model!$C$35 | E6: =A6*Model!$C$32*12
A7: 5 | B7: =A7*Model!$C$30*12 | C7: =A7*Model!$C$29*12 | D7: =A7*Model!$C$35 | E7: =A7*Model!$C$32*12
A8: 10 | B8: =A8*Model!$C$30*12 | C8: =A8*Model!$C$29*12 | D8: =A8*Model!$C$35 | E8: =A8*Model!$C$32*12
A9: 15 | B9: =A9*Model!$C$30*12 | C9: =A9*Model!$C$29*12 | D9: =A9*Model!$C$35 | E9: =A9*Model!$C$32*12
A10: 20 | B10: =A10*Model!$C$30*12 | C10: =A10*Model!$C$29*12 | D10: =A10*Model!$C$35 | E10: =A10*Model!$C$32*12
A12: Solo + AI operating ceiling ≈ 15–20 live instances before support/ops needs a hire.
A14: ALL THREE MODELS at current inputs (fleet, $/yr)
A15: Model | B15: A: Flat % | C15: B: Intchg-plus | D15: C: Membership
A16: Fleet total revenue ($/yr) | B16: =Model!B36 | C16: =Model!C36 | D16: =Model!D36
A17: Fleet contribution ($/yr) | B17: =Model!B37 | C17: =Model!C37 | D17: =Model!D37
A18: Of total: from payments (%) | B18: =IF(Model!B31=0,0,Model!B29/Model!B31) | C18: =IF(Model!C31=0,0,Model!C29/Model!C31) | D18: =IF(Model!D31=0,0,Model!D29/Model!D31)
A20: Read: Model A earns the most but taxes sales like Square; C earns least but is purest 'we charge for software'. B balances. Watch row 18 — a % markup on six-figure volume can quietly become your biggest line (that's why Toast leans on payments).

Sheet Assumptions & Notes
A1: Assumptions, Rate References & Strategy Notes
A3: THE COST STACK (every card txn)
A4: • Interchange (issuing bank): ~1.5–2.2% + ~$0.10 card-present. Non-negotiable.
A5: • Network assessments (Visa/MC): ~0.13–0.14%. Non-negotiable.
A6: • Processor / payfac markup: the only negotiable layer. Interchange (~2.0–2.3% all-in) is the floor nobody beats.
A8: MARKET REFERENCE RATES (merchant-facing, card-present)
A9: • Square: 2.6% + $0.15 in-person; 2.9% + $0.30 online.
A10: • Stripe: Terminal ~2.7% + $0.05 card-present; 2.9% + $0.30 online.
A11: • Toast: custom; ~2.49–2.99% + $0.15; offers interchange-plus to larger merchants.
A12: Source: public published rates, 2024–2025; rates move — treat as order-of-magnitude.
A14: YOUR COST BASIS (Model sheet, yellow cells)
A15: • Default 2.10% + $0.08 = interchange-plus via a payfac at modest volume.
... A34: • Excludes: hardware, chargeback losses, support cost per account, taxes. This models revenue/contribution, not full P&L.
